DataScryer-0.0.4.data/scripts/dataScryer.py
DataScryer-0.0.4.dist-info/DESCRIPTION.rst
DataScryer-0.0.4.dist-info/METADATA
DataScryer-0.0.4.dist-info/RECORD
DataScryer-0.0.4.dist-info/WHEEL
DataScryer-0.0.4.dist-info/metadata.json
DataScryer-0.0.4.dist-info/top_level.txt
DataScryer-0.0.4.dist-info/zip-safe
datascryer/__init__.py
datascryer/__init__.pyc
datascryer/config.py
datascryer/config.pyc
datascryer/livestatus.py
datascryer/livestatus.pyc
datascryer/__pycache__/__init__.cpython-35.pyc
datascryer/__pycache__/config.cpython-35.pyc
datascryer/__pycache__/livestatus.cpython-35.pyc
datascryer/default_methods/__init__.py
datascryer/default_methods/__init__.pyc
datascryer/default_methods/holt_winters.py
datascryer/default_methods/holt_winters.pyc
datascryer/default_methods/holt_winters_anomaly.py
datascryer/default_methods/out.txt
datascryer/default_methods/simple_linear_regression.py
datascryer/default_methods/simple_linear_regression.pyc
datascryer/default_methods/ssh.csv
datascryer/default_methods/stddev_anomaly.py
datascryer/default_methods/__pycache__/__init__.cpython-35.pyc
datascryer/default_methods/__pycache__/holt_winters.cpython-35.pyc
datascryer/default_methods/__pycache__/simple_linear_regression.cpython-35.pyc
datascryer/default_methods/__pycache__/stddev_anomaly.cpython-35.pyc
datascryer/helper/__init__.py
datascryer/helper/__init__.pyc
datascryer/helper/http.py
datascryer/helper/http.pyc
datascryer/helper/python.py
datascryer/helper/python.pyc
datascryer/helper/time_converter.py
datascryer/helper/time_converter.pyc
datascryer/helper/__pycache__/__init__.cpython-35.pyc
datascryer/helper/__pycache__/http.cpython-35.pyc
datascryer/helper/__pycache__/python.cpython-35.pyc
datascryer/helper/__pycache__/time_converter.cpython-35.pyc
datascryer/histou/__init__.py
datascryer/histou/__init__.pyc
datascryer/histou/histou.py
datascryer/histou/histou.pyc
datascryer/histou/__pycache__/__init__.cpython-35.pyc
datascryer/histou/__pycache__/histou.cpython-35.pyc
datascryer/influxdb/__init__.py
datascryer/influxdb/__init__.pyc
datascryer/influxdb/connection.py
datascryer/influxdb/connection.pyc
datascryer/influxdb/reader.py
datascryer/influxdb/reader.pyc
