Metadata-Version: 2.0
Name: DataScryer
Version: 0.0.4
Summary: DataScryer - Framework to predict future performancedata.
Home-page: https://github.com/Griesbacher/dataScryer
Author: Philip Griesbacher
Author-email: philip.griesbacher@consol.de
License: GPLv3
Platform: UNKNOWN
Classifier: Programming Language :: Python :: 2
Classifier: Programming Language :: Python :: 3
Requires-Dist: requests
